__init__.py
colors.py
errors.py
pickledbg.py
util.py
pickledbg-2.2.0.dist-info/licenses/LICENSE
pickledbg-2.2.0.dist-info/METADATA
pickledbg-2.2.0.dist-info/WHEEL
pickledbg-2.2.0.dist-info/entry_points.txt
pickledbg-2.2.0.dist-info/top_level.txt
pickledbg-2.2.0.dist-info/RECORD
