Metadata-Version: 2.4
Name: pickledbg
Version: 2.2.0
Summary: A GDB+GEF-style debugger, where pickles are unpacked instruction by instruction
Author: Legoclones
License-Expression: MIT
Project-URL: Homepage, https://github.com/Legoclones/pickledbg
Project-URL: Issues, https://github.com/Legoclones/pickledbg/issues
Classifier: Programming Language :: Python :: 3
Classifier: Operating System :: OS Independent
Requires-Python: >=3.6
License-File: LICENSE
Dynamic: license-file
